flytekitplugins_bigquery-1.16.12-py3.14-nspkg.pth
flytekitplugins/bigquery/__init__.py
flytekitplugins/bigquery/connector.py
flytekitplugins/bigquery/task.py
flytekitplugins_bigquery-1.16.12.dist-info/METADATA
flytekitplugins_bigquery-1.16.12.dist-info/WHEEL
flytekitplugins_bigquery-1.16.12.dist-info/entry_points.txt
flytekitplugins_bigquery-1.16.12.dist-info/namespace_packages.txt
flytekitplugins_bigquery-1.16.12.dist-info/top_level.txt
flytekitplugins_bigquery-1.16.12.dist-info/RECORD
